{
  "analysis_period_days": 30,
  "stats": {
    "total_commits": 300,
    "total_authors": 15
  },
  "hotspots": [
    {
      "path": "lightrag/kg/postgres_impl.py",
      "changes": 30,
      "risk": "high"
    },
    {
      "path": "lightrag_webui/src/api/lightrag.ts",
      "changes": 20,
      "risk": "high"
    },
    {
      "path": "lightrag_webui/src/locales/en.json",
      "changes": 18,
      "risk": "high"
    },
    {
      "path": "lightrag_webui/src/locales/zh.json",
      "changes": 18,
      "risk": "high"
    },
    {
      "path": "tests/test_interactive_setup_outputs.py",
      "changes": 16,
      "risk": "high"
    },
    {
      "path": "lightrag_webui/package.json",
      "changes": 14,
      "risk": "medium"
    },
    {
      "path": "lightrag_webui/bun.lock",
      "changes": 14,
      "risk": "medium"
    },
    {
      "path": "README-zh.md",
      "changes": 13,
      "risk": "medium"
    },
    {
      "path": "lightrag/api/lightrag_server.py",
      "changes": 12,
      "risk": "medium"
    },
    {
      "path": "README.md",
      "changes": 12,
      "risk": "medium"
    },
    {
      "path": "env.example",
      "changes": 12,
      "risk": "medium"
    },
    {
      "path": "scripts/setup/lib/file_ops.sh",
      "changes": 12,
      "risk": "medium"
    },
    {
      "path": "lightrag/api/routers/workspace_routes.py",
      "changes": 10,
      "risk": "medium"
    },
    {
      "path": "lightrag_webui/src/components/workspace/WorkspaceManagerDialog.tsx",
      "changes": 10,
      "risk": "medium"
    },
    {
      "path": "lightrag_webui/src/components/workspace/WorkspaceManagerDialog.test.tsx",
      "changes": 9,
      "risk": "medium"
    },
    {
      "path": "lightrag/lightrag.py",
      "changes": 9,
      "risk": "medium"
    },
    {
      "path": "lightrag/api/config.py",
      "changes": 9,
      "risk": "medium"
    },
    {
      "path": "tests/test_prompt_config_routes.py",
      "changes": 8,
      "risk": "medium"
    },
    {
      "path": "lightrag_webui/src/features/GraphViewer.tsx",
      "changes": 8,
      "risk": "medium"
    },
    {
      "path": "scripts/setup/setup.sh",
      "changes": 8,
      "risk": "medium"
    }
  ],
  "coupling_pairs": [
    {
      "file_a": "lightrag_webui/src/locales/en.json",
      "file_b": "lightrag_webui/src/locales/zh.json",
      "co_changes": 18,
      "coupling_score": 1.0
    },
    {
      "file_a": "lightrag_webui/bun.lock",
      "file_b": "lightrag_webui/package.json",
      "co_changes": 13,
      "coupling_score": 0.929
    },
    {
      "file_a": "README-zh.md",
      "file_b": "README.md",
      "co_changes": 12,
      "coupling_score": 1.0
    },
    {
      "file_a": "scripts/setup/lib/file_ops.sh",
      "file_b": "tests/test_interactive_setup_outputs.py",
      "co_changes": 12,
      "coupling_score": 1.0
    },
    {
      "file_a": "lightrag_webui/src/api/lightrag.ts",
      "file_b": "lightrag_webui/src/locales/en.json",
      "co_changes": 11,
      "coupling_score": 0.611
    },
    {
      "file_a": "lightrag_webui/src/api/lightrag.ts",
      "file_b": "lightrag_webui/src/locales/zh.json",
      "co_changes": 11,
      "coupling_score": 0.611
    },
    {
      "file_a": "lightrag_webui/src/components/workspace/WorkspaceManagerDialog.test.tsx",
      "file_b": "lightrag_webui/src/components/workspace/WorkspaceManagerDialog.tsx",
      "co_changes": 9,
      "coupling_score": 1.0
    },
    {
      "file_a": "lightrag/api/lightrag_server.py",
      "file_b": "lightrag/api/routers/workspace_routes.py",
      "co_changes": 7,
      "coupling_score": 0.7
    },
    {
      "file_a": "lightrag/api/lightrag_server.py",
      "file_b": "tests/test_prompt_config_routes.py",
      "co_changes": 7,
      "coupling_score": 0.875
    },
    {
      "file_a": "lightrag/api/routers/workspace_routes.py",
      "file_b": "tests/test_workspace_management_routes.py",
      "co_changes": 7,
      "coupling_score": 1.0
    },
    {
      "file_a": "lightrag/api/routers/workspace_routes.py",
      "file_b": "tests/test_prompt_config_routes.py",
      "co_changes": 6,
      "coupling_score": 0.75
    },
    {
      "file_a": "lightrag_webui/src/api/lightrag.test.ts",
      "file_b": "lightrag_webui/src/api/lightrag.ts",
      "co_changes": 6,
      "coupling_score": 1.0
    },
    {
      "file_a": "lightrag/api/config.py",
      "file_b": "lightrag/api/lightrag_server.py",
      "co_changes": 6,
      "coupling_score": 0.667
    },
    {
      "file_a": "lightrag_webui/src/locales/ar.json",
      "file_b": "lightrag_webui/src/locales/de.json",
      "co_changes": 6,
      "coupling_score": 1.0
    },
    {
      "file_a": "lightrag_webui/src/locales/ar.json",
      "file_b": "lightrag_webui/src/locales/en.json",
      "co_changes": 6,
      "coupling_score": 1.0
    },
    {
      "file_a": "lightrag_webui/src/locales/ar.json",
      "file_b": "lightrag_webui/src/locales/fr.json",
      "co_changes": 6,
      "coupling_score": 1.0
    },
    {
      "file_a": "lightrag_webui/src/locales/ar.json",
      "file_b": "lightrag_webui/src/locales/ja.json",
      "co_changes": 6,
      "coupling_score": 1.0
    },
    {
      "file_a": "lightrag_webui/src/locales/ar.json",
      "file_b": "lightrag_webui/src/locales/ko.json",
      "co_changes": 6,
      "coupling_score": 1.0
    },
    {
      "file_a": "lightrag_webui/src/locales/ar.json",
      "file_b": "lightrag_webui/src/locales/ru.json",
      "co_changes": 6,
      "coupling_score": 1.0
    },
    {
      "file_a": "lightrag_webui/src/locales/ar.json",
      "file_b": "lightrag_webui/src/locales/uk.json",
      "co_changes": 6,
      "coupling_score": 1.0
    }
  ]
}
